genie.parsergen-19.12-py3.4-nspkg.pth
genie/parsergen/__init__.py
genie/parsergen/_parsergen.cpython-34m.so
genie/parsergen/core.cpython-34m.so
genie/parsergen/examples/__init__.py
genie/parsergen/examples/parsergen/__init__.py
genie/parsergen/examples/parsergen/demo/nontabular_example.cpython-34m.so
genie/parsergen/examples/parsergen/demo/nontabular_markup.cpython-34m.so
genie/parsergen/examples/parsergen/demo/tabular_example.cpython-34m.so
genie/parsergen/examples/parsergen/pyAts/__init__.py
genie/parsergen/examples/parsergen/pyAts/parsergen_demo.cpython-34m.so
genie/parsergen/examples/parsergen/pyAts/parsergen_demo_aireos.cpython-34m.so
genie/parsergen/examples/parsergen/pyAts/parsergen_demo_aireos_conn_alias.cpython-34m.so
genie/parsergen/examples/parsergen/pyAts/parsergen_demo_aireos_job.cpython-34m.so
genie/parsergen/examples/parsergen/pyAts/parsergen_demo_aireos_job_conn_alias.cpython-34m.so
genie/parsergen/examples/parsergen/pyAts/parsergen_demo_conn_alias.cpython-34m.so
genie/parsergen/examples/parsergen/pyAts/parsergen_demo_enxr_job.cpython-34m.so
genie/parsergen/examples/parsergen/pyAts/parsergen_demo_enxr_job_conn_alias.cpython-34m.so
genie/parsergen/examples/parsergen/pyAts/parsergen_demo_mkpg.cpython-34m.so
genie/parsergen/examples/parsergen/pyAts/parsergen_demo_vios_job.cpython-34m.so
genie/parsergen/examples/parsergen/pyAts/parsergen_demo_viosxe_job.cpython-34m.so
genie/parsergen/examples/parsergen/pyAts/parsergen_demo_vnxos_job.cpython-34m.so
genie/parsergen/examples/parsergen/pyAts/parsergen_demo_xrvr_job.cpython-34m.so
genie/parsergen/examples/parsergen/pyAtsStandaloneUt/__init__.py
genie/parsergen/examples/parsergen/pyAtsStandaloneUt/cli_command_formatting_example.cpython-34m.so
genie/parsergen/examples/parsergen/pyAtsStandaloneUt/nontabular_parser_vios.cpython-34m.so
genie/parsergen/examples/parsergen/pyAtsStandaloneUt/nontabular_parser_viosxe.cpython-34m.so
genie.parsergen-19.12.dist-info/METADATA
genie.parsergen-19.12.dist-info/WHEEL
genie.parsergen-19.12.dist-info/namespace_packages.txt
genie.parsergen-19.12.dist-info/top_level.txt
genie.parsergen-19.12.dist-info/RECORD
